[
    {
        "Enseignant": {
            "mail": "vincent.trenchant@eseo.fr",
            "nom": "trenchant",
            "prenom": "vincent"
        },
        "GroupeEtudiant": {
            "nom": "E4"
        },
        "HeuresRestantes": {
            "CM": 4
        },
        "HeuresTotales": {
            "CM": 4
        },
        "Nom": "Math2"
    },
    {
        "Enseignant": {
            "mail": "vincent.trenchant@eseo.fr",
            "nom": "trenchant",
            "prenom": "vincent"
        },
        "GroupeEtudiant": {
            "nom": "E4"
        },
        "HeuresRestantes": {
            "CM": 8,
            "EXAMEN_EN_SALLE": 2,
            "TD": 6
        },
        "HeuresTotales": {
            "CM": 8,
            "EXAMEN_EN_SALLE": 2,
            "TD": 6
        },
        "Nom": "Signaux et Systemes"
    },
    {
        "Enseignant": {
            "mail": "vincent.trenchant@eseo.fr",
            "nom": "vincent",
            "prenom": "trenchant"
        },
        "GroupeEtudiant": {
            "nom": "E5"
        },
        "HeuresRestantes": {
            "CM": 4,
            "TD": 14
        },
        "HeuresTotales": {
            "CM": 4,
            "TD": 14
        },
        "Nom": "A"
    }
]
